{
  "id": "lists",
  "name": "stack of listings",
  "description": "You see stack of listings.",
  "examineText": "It's stack of listings.",
  "aliases": [
    "LISTS",
    "PAPER",
    "LIST",
    "PRINT",
    "LISTI",
    "STACK",
    "OUTPU",
    "GIGAN",
    "LINE-"
  ],
  "type": "TOOL",
  "portable": true,
  "visible": true,
  "weight": 70,
  "size": "HUGE",
  "initialState": {},
  "tags": [
    "flammable",
    "portable",
    "readable",
    "visible"
  ],
  "properties": {
    "size": 70,
    "readable": true
  },
  "interactions": [
    {
      "command": "examine",
      "message": "It's stack of listings."
    },
    {
      "command": "take",
      "message": "You take the stack of listings."
    },
    {
      "command": "read",
      "message": "You read the LISTS."
    }
  ],
  "initialLocation": "unknown"
}