{
  "id": "vault",
  "name": "large stone cube",
  "description": "You see large stone cube.",
  "examineText": "It's large stone cube.",
  "aliases": [
    "VAULT",
    "CUBE",
    "LETTE",
    "STONE",
    "LARGE"
  ],
  "type": "TOOL",
  "portable": false,
  "visible": true,
  "weight": 5,
  "size": "TINY",
  "initialState": {},
  "tags": [
    "visible",
    "readable"
  ],
  "properties": {
    "readText": "\t        Bank of Zork\n\t\t   VAULT\n         \t *722 GUE*\n          Frobozz Magic Vault Company\n",
    "readable": true
  },
  "interactions": [
    {
      "command": "examine",
      "message": "It's large stone cube."
    },
    {
      "command": "read",
      "message": "You read the large stone cube."
    }
  ],
  "initialLocation": "unknown"
}